stabledynamics/__init__.py
stabledynamics-0.1.dist-info/licenses/LICENSE
stabledynamics-0.1.dist-info/METADATA
stabledynamics-0.1.dist-info/WHEEL
stabledynamics-0.1.dist-info/top_level.txt
stabledynamics-0.1.dist-info/RECORD
