Metadata-Version: 2.4
Name: stabledynamics
Version: 0.1
Summary: `stabledynamics`: Stabilizing learned dynamical systems
Home-page: https://github.com/alisiahkoohi/stabledynamics
Author: Ali Siahkoohi
Author-email: alisk@rice.edu
Classifier: Programming Language :: Python :: 3
Classifier: License :: OSI Approved :: MIT License
Classifier: Operating System :: OS Independent
Requires-Python: >=3.10
License-File: LICENSE
Requires-Dist: tqdm
Requires-Dist: h5py
Requires-Dist: gitpython
Requires-Dist: matplotlib
Requires-Dist: projorg
Dynamic: license-file
